id_validator/__init__.py
id_validator/data.py
id_validator/func.py
id_validator/helper.py
id_validator/utils.py
id_validator/validator.py
id_validator-1.0.19.dist-info/LICENSE
id_validator-1.0.19.dist-info/METADATA
id_validator-1.0.19.dist-info/WHEEL
id_validator-1.0.19.dist-info/top_level.txt
id_validator-1.0.19.dist-info/RECORD
